cbwheelstreamtest/__init__.py
cbwheelstreamtest/__injt__.py
cbwheelstreamtest-0.0.1.dist-info/WHEEL
cbwheelstreamtest-0.0.1.dist-info/METADATA
cbwheelstreamtest-0.0.1.dist-info/RECORD
