Metadata-Version: 2.4
Name: cbwheelstreamtest
Version: 0.0.1
Summary: Another mysterious Python package
Author-email: Caleb <calebbrown@google.com>
